[
    {
        "productId": 1,
        "name": "Margherita Pizza",
        "isVeg": true,
        "image": "https://example.com/margherita.jpg",
        "description": "Classic Italian pizza topped with tomato sauce, fresh mozzarella cheese, and basil leaves.",
        "price": 10.99
    },
    {
        "productId": 2,
        "name": "Pepperoni Pizza",
        "isVeg": false,
        "image": "https://example.com/pepperoni.jpg",
        "description": "Traditional pizza topped with spicy pepperoni slices and melted cheese.",
        "price": 12.99
    },
    {
        "productId": 3,
        "name": "Vegetarian Pizza",
        "isVeg": true,
        "image": "https://example.com/vegetarian.jpg",
        "description": "A delicious medley of fresh vegetables such as bell peppers, mushrooms, onions, and olives on a bed of tomato sauce and cheese.",
        "price": 11.99
    },
    {
        "productId": 4,
        "name": "Hawaiian Pizza",
        "isVeg": false,
        "image": "https://example.com/hawaiian.jpg",
        "description": "A controversial yet beloved combination of ham, pineapple, and cheese on a thin crust.",
        "price": 13.49
    },
    {
        "productId": 5,
        "name": "BBQ Chicken Pizza",
        "isVeg": false,
        "image": "https://example.com/bbq-chicken.jpg",
        "description": "Tender grilled chicken pieces marinated in barbecue sauce, topped with red onions, and smothered in melted cheese.",
        "price": 14.99
    },
    {
        "productId": 6,
        "name": "Mushroom Pizza",
        "isVeg": true,
        "image": "https://example.com/mushroom.jpg",
        "description": "Sliced mushrooms sautéed in garlic butter and herbs, generously spread over a cheesy base.",
        "price": 11.49
    },
    {
        "productId": 7,
        "name": "Four Cheese Pizza",
        "isVeg": true,
        "image": "https://example.com/four-cheese.jpg",
        "description": "A cheese lover's dream featuring a blend of mozzarella, cheddar, parmesan, and gorgonzola cheeses atop a crispy crust.",
        "price": 13.99
    },
    {
        "productId": 8,
        "name": "Meat Lover's Pizza",
        "isVeg": false,
        "image": "https://example.com/meat-lovers.jpg",
        "description": "Packed with a hearty assortment of meat toppings including pepperoni, sausage, ham, and bacon.",
        "price": 15.49
    },
    {
        "productId": 9,
        "name": "Spinach and Feta Pizza",
        "isVeg": true,
        "image": "https://example.com/spinach-feta.jpg",
        "description": "A light and flavorful option featuring sautéed spinach, tangy feta cheese, and a hint of garlic.",
        "price": 12.49
    },
    {
        "productId": 10,
        "name": "Buffalo Chicken Pizza",
        "isVeg": false,
        "image": "https://example.com/buffalo-chicken.jpg",
        "description": "Spicy buffalo chicken pieces combined with creamy ranch dressing and melted cheese on a crispy crust.",
        "price": 14.99
    }
]